tornado_mysql/__init__.py
tornado_mysql/_compat.py
tornado_mysql/charset.py
tornado_mysql/connections.py
tornado_mysql/converters.py
tornado_mysql/cursors.py
tornado_mysql/err.py
tornado_mysql/pools.py
tornado_mysql/times.py
tornado_mysql/util.py
tornado_mysql/constants/__init__.py
tornado_mysql/constants/CLIENT.py
tornado_mysql/constants/COMMAND.py
tornado_mysql/constants/ER.py
tornado_mysql/constants/FIELD_TYPE.py
tornado_mysql/constants/FLAG.py
tornado_mysql/constants/SERVER_STATUS.py
tornado_mysql/tests/__init__.py
tornado_mysql/tests/base.py
tornado_mysql/tests/test_basic.py
tornado_mysql/tests/test_connection.py
tornado_mysql/tests/test_cursor.py
tornado_mysql/tests/test_DictCursor.py
tornado_mysql/tests/test_example.py
tornado_mysql/tests/test_issues.py
tornado_mysql/tests/test_load_local.py
tornado_mysql/tests/test_nextset.py
tornado_mysql/tests/test_SSCursor.py
tornado_mysql/tests/thirdparty/__init__.py
tornado_mysql/tests/thirdparty/test_MySQLdb/__init__.py
tornado_mysql/tests/thirdparty/test_MySQLdb/capabilities.py
tornado_mysql/tests/thirdparty/test_MySQLdb/dbapi20.py
tornado_mysql/tests/thirdparty/test_MySQLdb/test_MySQLdb_capabilities.py
tornado_mysql/tests/thirdparty/test_MySQLdb/test_MySQLdb_dbapi20.py
tornado_mysql/tests/thirdparty/test_MySQLdb/test_MySQLdb_nonstandard.py
Tornado_MySQL-0.5.1.dist-info/DESCRIPTION.rst
Tornado_MySQL-0.5.1.dist-info/METADATA
Tornado_MySQL-0.5.1.dist-info/metadata.json
Tornado_MySQL-0.5.1.dist-info/pbr.json
Tornado_MySQL-0.5.1.dist-info/RECORD
Tornado_MySQL-0.5.1.dist-info/top_level.txt
Tornado_MySQL-0.5.1.dist-info/WHEEL
